mailSenderSU/__init__.py
mailSenderSU/cli.py
mailSenderSU/data/signature.html
mailSenderSU/img/polytech.gif
mailSenderSU/img/su.gif
mailSenderSU/src/attachments.py
mailSenderSU/src/email_utils.py
mailSenderSU/src/files.py
mailSenderSU/src/login_interface.py
mailSenderSU/src/mail_interface.py
mailSenderSU/src/message.py
mailSenderSU/src/style.py
mailSenderSU-1.0.0.dist-info/LICENSE
mailSenderSU-1.0.0.dist-info/METADATA
mailSenderSU-1.0.0.dist-info/WHEEL
mailSenderSU-1.0.0.dist-info/entry_points.txt
mailSenderSU-1.0.0.dist-info/top_level.txt
mailSenderSU-1.0.0.dist-info/zip-safe
mailSenderSU-1.0.0.dist-info/RECORD
