Metadata-Version: 2.1
Name: mailSenderSU
Version: 1.0.0
Summary: Mail sender for Sorbonne-University
Home-page: https://github.com/Quentin18/Mail-Sender-Sorbonne-Universite
Author: Quentin Deschamps
Author-email: quentindeschamps18@gmail.com
License: MIT
Project-URL: Documentation, https://mail-sender-sorbonne-universite.readthedocs.io/fr/latest/
Project-URL: Travis, https://travis-ci.org/Quentin18/Mail-Sender-Sorbonne-Universite/
Project-URL: Source Code, https://github.com/Quentin18/Mail-Sender-Sorbonne-Universite/
Keywords: mail sender python sorbonne-university
Platform: any
Classifier: License :: OSI Approved :: MIT License
Classifier: Natural Language :: French
Classifier: Operating System :: OS Independent
Classifier: Programming Language :: Python :: 3
Classifier: Programming Language :: Python :: 3.6
Classifier: Programming Language :: Python :: 3.7
Classifier: Programming Language :: Python :: 3.8
Classifier: Topic :: Communications :: Email
Requires-Python: >=3.6
Requires-Dist: click
